{
  "$schema": "../gen/schemas/desktop-schema.json",
  "identifier": "default",
  "description": "Capability for the main window",
  "windows": ["*"],
  "permissions": [
    "core:default",
    "core:window:allow-close",
    "core:window:allow-create",
    "core:window:allow-hide",
    "core:window:allow-is-fullscreen",
    "core:window:allow-maximize",
    "core:window:allow-minimize",
    "core:window:allow-set-focus",
    "core:window:allow-show",
    "core:window:allow-set-fullscreen",
    "core:window:allow-unmaximize",
    "dialog:default",
    "opener:default"
  ]
}
